Metadata-Version: 1.0
Name: logincraw
Version: 1.0
Summary: login craw library
Home-page: http://test.com
Author: aaronhua
Author-email: cjhdwyyx@163.com
License: UNKNOWN
Platform: all
